{"_id":{"$oid":"68bad11c189f86d5e1962cde"},"goods_banner_imgs":["https://mp-f18d6178-7240-42d3-98b7-73076158595e.cdn.bspapp.com/admin/20250905/1757073690945.webp","https://mp-f18d6178-7240-42d3-98b7-73076158595e.cdn.bspapp.com/admin/20250905/1757073690644.webp","https://mp-f18d6178-7240-42d3-98b7-73076158595e.cdn.bspapp.com/admin/20250905/1757073690652.webp"],"create_date":1757073693109,"last_modify_date":1762820141162,"name":"12","category_id":{"$oid":"68bace1109664cca9827a788"},"is_on_sale":false,"is_hot":false,"goods_desc":"<p>12</p>","sku":[{"weight":499,"status":true,"_id":"mf6safqt0f6f","name":"1","price":100,"market_price":200},{"weight":500,"status":true,"_id":"mhttksekcmja","name":"换洒洒水水水","price":100,"market_price":2000}]}
{"_id":{"$oid":"67f745cd7ae708f08a72cc42"},"dstype":0,"create_date":1744258508382,"category_id":{"$oid":"67b14e23a674f48993b82a64"},"name":"办事","sort":9,"sku":[{"weight":500,"status":true,"_id":"mhty0zoemvve","name":"1","price":100,"market_price":100}]}
{"_id":{"$oid":"677254ae7447023eda997521"},"name":"丧事","sort":9,"category_id":{"$oid":"676c63d5e0ec1956a9b6bb1b"},"sku":[{"weight":500,"status":true,"_id":"mhty0zoemvve","name":"1","price":100,"market_price":100}]}
{"_id":{"$oid":"67b150b60d2b3168f746b4a2"},"dstype":0,"create_date":1739673781330,"category_id":{"$oid":"67b14e23a674f48993b82a64"},"name":"丧事","sort":3,"sku":[{"weight":500,"status":true,"_id":"mhty0zoemvve","name":"1","price":100,"market_price":100}]}
{"_id":{"$oid":"681589891c90b6a2f149695f"},"dstype":0,"create_date":1746241929575,"category_id":{"$oid":"676c63879755e310b96f0e8c"},"name":"冷库","sort":1,"last_modify_date":1762200075211,"sku":[{"weight":500,"status":true,"_id":"mhty0zoemvve","name":"1","price":100,"market_price":100}]}
{"_id":{"$oid":"67b01c9be0ec19c8428c8142"},"dstype":0,"create_date":1739594907091,"category_id":{"$oid":"676c63879755e310b96f0e8c"},"name":"空调","sort":2,"is_on_sale":true,"last_modify_date":1762685766324,"sku":[{"weight":500,"status":true,"_id":"mhty0zoemvve","name":"1","price":100,"market_price":100}]}
{"_id":{"$oid":"67c04398189f86a8aea3eb9a"},"dstype":0,"create_date":1740653464247,"category_id":{"$oid":"67b541aa6523418be87fbd59"},"name":"打孔","sort":38,"last_modify_date":1762201021032,"is_on_sale":true,"sku":[{"weight":500,"status":true,"_id":"mhty0zoemvve","name":"1","price":100,"market_price":100}]}
{"_id":{"$oid":"677254ae7447023eda99752a"},"name":"液晶电视","sort":9,"category_id":{"$oid":"676c63879755e310b96f0e8c"},"last_modify_date":1762685998497,"sku":[{"weight":500,"status":true,"_id":"mhty0zoemvve","name":"1","price":100,"market_price":100}]}
{"_id":{"$oid":"67a81ebdce5ec9e5aae5ca16"},"create_date":1739071154310,"category_id":{"$oid":"676c645155b337bf5239177f"},"name":"空调","sort":4,"dstype":1,"sku":[{"weight":500,"status":true,"_id":"mhty0zoemvve","name":"1","price":100,"market_price":100}]}
{"_id":{"$oid":"67b53de7f2949cf7215a33b1"},"dstype":0,"create_date":1739931111080,"category_id":{"$oid":"676c63879755e310b96f0e8c"},"name":"太阳能","sort":6,"is_on_sale":false,"last_modify_date":1762685931493,"sku":[{"weight":500,"status":true,"_id":"mhty0zoemvve","name":"1","price":100,"market_price":100}]}
{"_id":{"$oid":"67b01cedee97ef1479299def"},"dstype":0,"create_date":1739594989151,"category_id":{"$oid":"676c63879755e310b96f0e8c"},"name":"洗衣机","sort":5,"last_modify_date":1762685892348,"sku":[{"weight":500,"status":true,"_id":"mhty0zoemvve","name":"1","price":100,"market_price":100}]}
{"_id":{"$oid":"67fb9cff189f86798fa987ca"},"dstype":0,"create_date":1744542975596,"category_id":{"$oid":"676c63879755e310b96f0e8c"},"name":"电脑","sort":4,"last_modify_date":1762685885566,"sku":[{"weight":500,"status":true,"_id":"mhty0zoemvve","name":"1","price":100,"market_price":100}]}
{"_id":{"$oid":"67cbc9c58b0da45f01e577f5"},"dstype":0,"create_date":1741408709203,"category_id":{"$oid":"67b541aa6523418be87fbd59"},"name":"疏通管道","sort":40,"sku":[{"weight":500,"status":true,"_id":"mhty0zoemvve","name":"1","price":100,"market_price":100}]}
{"_id":{"$oid":"681bc97f99c624aa844ad171"},"dstype":0,"create_date":1746651519850,"category_id":{"$oid":"676c63879755e310b96f0e8c"},"name":"空气能","sort":7,"is_on_sale":true,"last_modify_date":1762199642641,"sku":[{"weight":500,"status":true,"_id":"mhty0zoemvve","name":"1","price":100,"market_price":100}]}
{"_id":{"$oid":"6908744b6e5d2db044f0870c"},"last_modify_date":1762161738972,"name":"上门修汽车","category_id":{"$oid":"67b14e23a674f48993b82a64"},"is_on_sale":true,"sku":[{"weight":500,"status":true,"_id":"mhty0zoemvve","name":"1","price":100,"market_price":100}]}
{"_id":{"$oid":"677254ae7447023eda997520"},"name":"清洗油烟机","sort":1,"category_id":{"$oid":"676c63e41c90b6b5569a790f"},"sku":[{"weight":500,"status":true,"_id":"mhty0zoemvve","name":"1","price":100,"market_price":100}]}
{"_id":{"$oid":"67cc19513f1a473be2d20548"},"dstype":0,"create_date":1741429073339,"category_id":{"$oid":"676c63879755e310b96f0e8c"},"name":"手机","sort":9,"sku":[{"weight":500,"status":true,"_id":"mhty0zoemvve","name":"1","price":100,"market_price":100}]}
{"_id":{"$oid":"69129d5ff08210f2f1bf6c58"},"goods_banner_imgs":[],"create_date":1762827613446,"last_modify_date":1762829671496,"name":"c1","category_id":{"$oid":"676c63879755e310b96f0e8c"},"is_on_sale":true,"is_hot":false,"goods_desc":"","sku":[{"weight":1,"status":true,"_id":"mhty0zoemvve","name":"1","price":1,"market_price":100}]}